[
  {
    "data": {
      "id": "runSequence_1740422007562_357a4cc1-104b-4744-ab37-bd283b198067",
      "label": "runSequence",
      "narratives": [],
      "parallel": false,
      "abstract": false,
      "createTime": "2025-02-24T18:33:27.562Z",
      "parent": "runInDepth_1740422007561_06a04954-ac06-410e-970d-49648e9462b1",
      "inputs": [
        10
      ],
      "outputs": [
        "run for sequence: 5",
        "run for sequence: 5",
        "run for sequence: 5",
        "run for sequence: 5",
        "run for sequence: 5",
        "finished runSequenceInDepth for depth : 10"
      ],
      "startTime": "2025-02-24T18:33:27.562Z",
      "endTime": "2025-02-24T18:33:27.563Z",
      "duration": 0.6506249904632568,
      "elapsedTime": "0.651 ms",
      "updateTime": "2025-02-24T18:33:27.563Z"
    },
    "group": "nodes"
  },
  {
    "data": {
      "id": "task_1740422007562_b849d372-f07c-4a21-b478-36d083cc056c",
      "label": "task",
      "parent": "runSequence_1740422007562_357a4cc1-104b-4744-ab37-bd283b198067",
      "inputs": [
        5
      ],
      "outputs": "run for sequence: 5",
      "startTime": "2025-02-24T18:33:27.562Z",
      "endTime": "2025-02-24T18:33:27.562Z",
      "duration": 0.039041996002197266,
      "elapsedTime": "0.039 ms",
      "narratives": [],
      "parallel": false,
      "abstract": false,
      "createTime": "2025-02-24T18:33:27.562Z"
    },
    "group": "nodes"
  },
  {
    "data": {
      "id": "task_1740422007562_d572a969-ebcb-44ae-9a72-48aeffe9b0e2",
      "label": "task",
      "parent": "runSequence_1740422007562_357a4cc1-104b-4744-ab37-bd283b198067",
      "inputs": [
        5
      ],
      "outputs": "run for sequence: 5",
      "startTime": "2025-02-24T18:33:27.562Z",
      "endTime": "2025-02-24T18:33:27.562Z",
      "duration": 0.02245783805847168,
      "elapsedTime": "0.022 ms",
      "narratives": [],
      "parallel": false,
      "abstract": false,
      "createTime": "2025-02-24T18:33:27.563Z"
    },
    "group": "nodes"
  },
  {
    "data": {
      "id": "task_1740422007563_33003fe3-051a-4377-bec3-f9f4d96244ca",
      "label": "task",
      "parent": "runSequence_1740422007562_357a4cc1-104b-4744-ab37-bd283b198067",
      "inputs": [
        5
      ],
      "outputs": "run for sequence: 5",
      "startTime": "2025-02-24T18:33:27.563Z",
      "endTime": "2025-02-24T18:33:27.563Z",
      "duration": 0.07583308219909668,
      "elapsedTime": "0.076 ms",
      "narratives": [],
      "parallel": false,
      "abstract": false,
      "createTime": "2025-02-24T18:33:27.563Z"
    },
    "group": "nodes"
  },
  {
    "data": {
      "id": "task_1740422007563_de6de59d-0b63-4671-9052-3225cd30cefd",
      "label": "task",
      "parent": "runSequence_1740422007562_357a4cc1-104b-4744-ab37-bd283b198067",
      "inputs": [
        5
      ],
      "outputs": "run for sequence: 5",
      "startTime": "2025-02-24T18:33:27.563Z",
      "endTime": "2025-02-24T18:33:27.563Z",
      "duration": 0.012624979019165039,
      "elapsedTime": "0.013 ms",
      "narratives": [],
      "parallel": false,
      "abstract": false,
      "createTime": "2025-02-24T18:33:27.563Z"
    },
    "group": "nodes"
  },
  {
    "data": {
      "id": "task_1740422007563_7a7d8067-9f95-4042-8b9d-20a0d7d26dd3",
      "label": "task",
      "parent": "runSequence_1740422007562_357a4cc1-104b-4744-ab37-bd283b198067",
      "inputs": [
        5
      ],
      "outputs": "run for sequence: 5",
      "startTime": "2025-02-24T18:33:27.563Z",
      "endTime": "2025-02-24T18:33:27.563Z",
      "duration": 0.008249998092651367,
      "elapsedTime": "0.008 ms",
      "narratives": [],
      "parallel": false,
      "abstract": false,
      "createTime": "2025-02-24T18:33:27.563Z"
    },
    "group": "nodes"
  },
  {
    "data": {
      "id": "runInDepth_1740422007561_06a04954-ac06-410e-970d-49648e9462b1",
      "label": "runInDepth",
      "narratives": [],
      "parallel": false,
      "abstract": false,
      "createTime": "2025-02-24T18:33:27.563Z",
      "inputs": [
        [
          "starting"
        ]
      ],
      "outputs": "result1 for run for sequence: 5,run for sequence: 5,run for sequence: 5,run for sequence: 5,run for sequence: 5,finished runSequenceInDepth for depth : 1 at level 10",
      "startTime": "2025-02-24T18:33:27.562Z",
      "endTime": "2025-02-24T18:33:27.565Z",
      "duration": 3.48104190826416,
      "elapsedTime": "3.481 ms",
      "updateTime": "2025-02-24T18:33:27.565Z"
    },
    "group": "nodes"
  },
  {
    "data": {
      "id": "runSequence_1740422007563_c5c6bda0-011f-48fe-a6dd-4441b949247d",
      "label": "runSequence",
      "narratives": [],
      "parallel": false,
      "abstract": false,
      "createTime": "2025-02-24T18:33:27.563Z",
      "parent": "runInDepth_1740422007563_a262665a-caec-47fc-9f20-cb2424baf6c1",
      "inputs": [
        9
      ],
      "outputs": [
        "run for sequence: 5",
        "run for sequence: 5",
        "run for sequence: 5",
        "run for sequence: 5",
        "run for sequence: 5",
        "finished runSequenceInDepth for depth : 9"
      ],
      "startTime": "2025-02-24T18:33:27.563Z",
      "endTime": "2025-02-24T18:33:27.563Z",
      "duration": 0.3445000648498535,
      "elapsedTime": "0.345 ms",
      "updateTime": "2025-02-24T18:33:27.563Z"
    },
    "group": "nodes"
  },
  {
    "data": {
      "id": "task_1740422007563_633d000c-0d05-4307-a694-d62495e319da",
      "label": "task",
      "parent": "runSequence_1740422007563_c5c6bda0-011f-48fe-a6dd-4441b949247d",
      "inputs": [
        5
      ],
      "outputs": "run for sequence: 5",
      "startTime": "2025-02-24T18:33:27.563Z",
      "endTime": "2025-02-24T18:33:27.563Z",
      "duration": 0.00916600227355957,
      "elapsedTime": "0.009 ms",
      "narratives": [],
      "parallel": false,
      "abstract": false,
      "createTime": "2025-02-24T18:33:27.563Z"
    },
    "group": "nodes"
  },
  {
    "data": {
      "id": "task_1740422007563_fe514b76-670a-424a-8d10-3f632cb66562",
      "label": "task",
      "parent": "runSequence_1740422007563_c5c6bda0-011f-48fe-a6dd-4441b949247d",
      "inputs": [
        5
      ],
      "outputs": "run for sequence: 5",
      "startTime": "2025-02-24T18:33:27.563Z",
      "endTime": "2025-02-24T18:33:27.563Z",
      "duration": 0.005249977111816406,
      "elapsedTime": "0.005 ms",
      "narratives": [],
      "parallel": false,
      "abstract": false,
      "createTime": "2025-02-24T18:33:27.563Z"
    },
    "group": "nodes"
  },
  {
    "data": {
      "id": "task_1740422007563_83007135-966a-406c-af8a-b7e80818d168",
      "label": "task",
      "parent": "runSequence_1740422007563_c5c6bda0-011f-48fe-a6dd-4441b949247d",
      "inputs": [
        5
      ],
      "outputs": "run for sequence: 5",
      "startTime": "2025-02-24T18:33:27.563Z",
      "endTime": "2025-02-24T18:33:27.563Z",
      "duration": 0.005666017532348633,
      "elapsedTime": "0.006 ms",
      "narratives": [],
      "parallel": false,
      "abstract": false,
      "createTime": "2025-02-24T18:33:27.563Z"
    },
    "group": "nodes"
  },
  {
    "data": {
      "id": "task_1740422007563_fe0224ae-d66e-46f8-82ec-9aaac4067024",
      "label": "task",
      "parent": "runSequence_1740422007563_c5c6bda0-011f-48fe-a6dd-4441b949247d",
      "inputs": [
        5
      ],
      "outputs": "run for sequence: 5",
      "startTime": "2025-02-24T18:33:27.563Z",
      "endTime": "2025-02-24T18:33:27.563Z",
      "duration": 0.013916015625,
      "elapsedTime": "0.014 ms",
      "narratives": [],
      "parallel": false,
      "abstract": false,
      "createTime": "2025-02-24T18:33:27.563Z"
    },
    "group": "nodes"
  },
  {
    "data": {
      "id": "task_1740422007563_22baedef-1fb7-40df-97e8-ed434533f8f2",
      "label": "task",
      "parent": "runSequence_1740422007563_c5c6bda0-011f-48fe-a6dd-4441b949247d",
      "inputs": [
        5
      ],
      "outputs": "run for sequence: 5",
      "startTime": "2025-02-24T18:33:27.563Z",
      "endTime": "2025-02-24T18:33:27.563Z",
      "duration": 0.009417057037353516,
      "elapsedTime": "0.009 ms",
      "narratives": [],
      "parallel": false,
      "abstract": false,
      "createTime": "2025-02-24T18:33:27.563Z"
    },
    "group": "nodes"
  },
  {
    "data": {
      "id": "runInDepth_1740422007563_a262665a-caec-47fc-9f20-cb2424baf6c1",
      "label": "runInDepth",
      "narratives": [],
      "parallel": false,
      "abstract": false,
      "createTime": "2025-02-24T18:33:27.563Z",
      "parent": "runInDepth_1740422007561_06a04954-ac06-410e-970d-49648e9462b1",
      "inputs": [
        [
          "run for sequence: 5",
          "run for sequence: 5",
          "run for sequence: 5",
          "run for sequence: 5",
          "run for sequence: 5",
          "finished runSequenceInDepth for depth : 10"
        ]
      ],
      "outputs": "result1 for run for sequence: 5,run for sequence: 5,run for sequence: 5,run for sequence: 5,run for sequence: 5,finished runSequenceInDepth for depth : 1 at level 10",
      "startTime": "2025-02-24T18:33:27.563Z",
      "endTime": "2025-02-24T18:33:27.565Z",
      "duration": 2.4097909927368164,
      "elapsedTime": "2.410 ms",
      "updateTime": "2025-02-24T18:33:27.565Z"
    },
    "group": "nodes"
  },
  {
    "data": {
      "id": "runSequence_1740422007563_b7242f4b-2356-4e8f-820b-70ee024b3880",
      "label": "runSequence",
      "narratives": [],
      "parallel": false,
      "abstract": false,
      "createTime": "2025-02-24T18:33:27.563Z",
      "parent": "runInDepth_1740422007563_3b5c0e86-f548-4ee7-9534-8a0e20137f9f",
      "inputs": [
        8
      ],
      "outputs": [
        "run for sequence: 5",
        "run for sequence: 5",
        "run for sequence: 5",
        "run for sequence: 5",
        "run for sequence: 5",
        "finished runSequenceInDepth for depth : 8"
      ],
      "startTime": "2025-02-24T18:33:27.563Z",
      "endTime": "2025-02-24T18:33:27.564Z",
      "duration": 0.28816699981689453,
      "elapsedTime": "0.288 ms",
      "updateTime": "2025-02-24T18:33:27.564Z"
    },
    "group": "nodes"
  },
  {
    "data": {
      "id": "task_1740422007563_bbc6d69f-4e62-44d5-8418-2abfec07ee62",
      "label": "task",
      "parent": "runSequence_1740422007563_b7242f4b-2356-4e8f-820b-70ee024b3880",
      "inputs": [
        5
      ],
      "outputs": "run for sequence: 5",
      "startTime": "2025-02-24T18:33:27.563Z",
      "endTime": "2025-02-24T18:33:27.563Z",
      "duration": 0.006207942962646484,
      "elapsedTime": "0.006 ms",
      "narratives": [],
      "parallel": false,
      "abstract": false,
      "createTime": "2025-02-24T18:33:27.563Z"
    },
    "group": "nodes"
  },
  {
    "data": {
      "id": "task_1740422007563_6a91561a-ec41-41d0-b7b2-7b1fbfe16b94",
      "label": "task",
      "parent": "runSequence_1740422007563_b7242f4b-2356-4e8f-820b-70ee024b3880",
      "inputs": [
        5
      ],
      "outputs": "run for sequence: 5",
      "startTime": "2025-02-24T18:33:27.563Z",
      "endTime": "2025-02-24T18:33:27.563Z",
      "duration": 0.006875038146972656,
      "elapsedTime": "0.007 ms",
      "narratives": [],
      "parallel": false,
      "abstract": false,
      "createTime": "2025-02-24T18:33:27.563Z"
    },
    "group": "nodes"
  },
  {
    "data": {
      "id": "task_1740422007563_e80c31ae-92c0-4863-aed3-08f97c03e248",
      "label": "task",
      "parent": "runSequence_1740422007563_b7242f4b-2356-4e8f-820b-70ee024b3880",
      "inputs": [
        5
      ],
      "outputs": "run for sequence: 5",
      "startTime": "2025-02-24T18:33:27.563Z",
      "endTime": "2025-02-24T18:33:27.563Z",
      "duration": 0.00475001335144043,
      "elapsedTime": "0.005 ms",
      "narratives": [],
      "parallel": false,
      "abstract": false,
      "createTime": "2025-02-24T18:33:27.563Z"
    },
    "group": "nodes"
  },
  {
    "data": {
      "id": "task_1740422007563_a75822e7-f82d-4dba-b846-1c010135cd7d",
      "label": "task",
      "parent": "runSequence_1740422007563_b7242f4b-2356-4e8f-820b-70ee024b3880",
      "inputs": [
        5
      ],
      "outputs": "run for sequence: 5",
      "startTime": "2025-02-24T18:33:27.563Z",
      "endTime": "2025-02-24T18:33:27.563Z",
      "duration": 0.004374980926513672,
      "elapsedTime": "0.004 ms",
      "narratives": [],
      "parallel": false,
      "abstract": false,
      "createTime": "2025-02-24T18:33:27.563Z"
    },
    "group": "nodes"
  },
  {
    "data": {
      "id": "task_1740422007563_d91200d3-e548-4023-8e0f-8f8023e1e0f7",
      "label": "task",
      "parent": "runSequence_1740422007563_b7242f4b-2356-4e8f-820b-70ee024b3880",
      "inputs": [
        5
      ],
      "outputs": "run for sequence: 5",
      "startTime": "2025-02-24T18:33:27.563Z",
      "endTime": "2025-02-24T18:33:27.563Z",
      "duration": 0.004292011260986328,
      "elapsedTime": "0.004 ms",
      "narratives": [],
      "parallel": false,
      "abstract": false,
      "createTime": "2025-02-24T18:33:27.563Z"
    },
    "group": "nodes"
  },
  {
    "data": {
      "id": "runInDepth_1740422007563_3b5c0e86-f548-4ee7-9534-8a0e20137f9f",
      "label": "runInDepth",
      "narratives": [],
      "parallel": false,
      "abstract": false,
      "createTime": "2025-02-24T18:33:27.564Z",
      "parent": "runInDepth_1740422007563_a262665a-caec-47fc-9f20-cb2424baf6c1",
      "inputs": [
        [
          "run for sequence: 5",
          "run for sequence: 5",
          "run for sequence: 5",
          "run for sequence: 5",
          "run for sequence: 5",
          "finished runSequenceInDepth for depth : 9"
        ]
      ],
      "outputs": "result1 for run for sequence: 5,run for sequence: 5,run for sequence: 5,run for sequence: 5,run for sequence: 5,finished runSequenceInDepth for depth : 1 at level 10",
      "startTime": "2025-02-24T18:33:27.563Z",
      "endTime": "2025-02-24T18:33:27.565Z",
      "duration": 1.9517910480499268,
      "elapsedTime": "1.952 ms",
      "updateTime": "2025-02-24T18:33:27.565Z"
    },
    "group": "nodes"
  },
  {
    "data": {
      "id": "runSequence_1740422007564_37f7b0cc-812c-42d2-90d1-f10c9b15f967",
      "label": "runSequence",
      "narratives": [],
      "parallel": false,
      "abstract": false,
      "createTime": "2025-02-24T18:33:27.564Z",
      "parent": "runInDepth_1740422007564_01cc5f8e-a4aa-4283-b9f3-341f1860d9f6",
      "inputs": [
        7
      ],
      "outputs": [
        "run for sequence: 5",
        "run for sequence: 5",
        "run for sequence: 5",
        "run for sequence: 5",
        "run for sequence: 5",
        "finished runSequenceInDepth for depth : 7"
      ],
      "startTime": "2025-02-24T18:33:27.564Z",
      "endTime": "2025-02-24T18:33:27.564Z",
      "duration": 0.11962485313415527,
      "elapsedTime": "0.120 ms",
      "updateTime": "2025-02-24T18:33:27.564Z"
    },
    "group": "nodes"
  },
  {
    "data": {
      "id": "task_1740422007564_19b9d44a-ce12-47a8-93eb-8035a685356f",
      "label": "task",
      "parent": "runSequence_1740422007564_37f7b0cc-812c-42d2-90d1-f10c9b15f967",
      "inputs": [
        5
      ],
      "outputs": "run for sequence: 5",
      "startTime": "2025-02-24T18:33:27.564Z",
      "endTime": "2025-02-24T18:33:27.564Z",
      "duration": 0.0038328170776367188,
      "elapsedTime": "0.004 ms",
      "narratives": [],
      "parallel": false,
      "abstract": false,
      "createTime": "2025-02-24T18:33:27.564Z"
    },
    "group": "nodes"
  },
  {
    "data": {
      "id": "task_1740422007564_0ed8549c-6d69-4343-866a-334a8689eb7c",
      "label": "task",
      "parent": "runSequence_1740422007564_37f7b0cc-812c-42d2-90d1-f10c9b15f967",
      "inputs": [
        5
      ],
      "outputs": "run for sequence: 5",
      "startTime": "2025-02-24T18:33:27.564Z",
      "endTime": "2025-02-24T18:33:27.564Z",
      "duration": 0.0038750171661376953,
      "elapsedTime": "0.004 ms",
      "narratives": [],
      "parallel": false,
      "abstract": false,
      "createTime": "2025-02-24T18:33:27.564Z"
    },
    "group": "nodes"
  },
  {
    "data": {
      "id": "task_1740422007564_d27bb713-700f-4e36-9512-0ae06cd31c8b",
      "label": "task",
      "parent": "runSequence_1740422007564_37f7b0cc-812c-42d2-90d1-f10c9b15f967",
      "inputs": [
        5
      ],
      "outputs": "run for sequence: 5",
      "startTime": "2025-02-24T18:33:27.564Z",
      "endTime": "2025-02-24T18:33:27.564Z",
      "duration": 0.003917217254638672,
      "elapsedTime": "0.004 ms",
      "narratives": [],
      "parallel": false,
      "abstract": false,
      "createTime": "2025-02-24T18:33:27.564Z"
    },
    "group": "nodes"
  },
  {
    "data": {
      "id": "task_1740422007564_b5869e87-f4a8-497e-8b85-a9a558b2979f",
      "label": "task",
      "parent": "runSequence_1740422007564_37f7b0cc-812c-42d2-90d1-f10c9b15f967",
      "inputs": [
        5
      ],
      "outputs": "run for sequence: 5",
      "startTime": "2025-02-24T18:33:27.564Z",
      "endTime": "2025-02-24T18:33:27.564Z",
      "duration": 0.0038340091705322266,
      "elapsedTime": "0.004 ms",
      "narratives": [],
      "parallel": false,
      "abstract": false,
      "createTime": "2025-02-24T18:33:27.564Z"
    },
    "group": "nodes"
  },
  {
    "data": {
      "id": "task_1740422007564_3e836c79-df37-4872-93a2-04a2c0c690f4",
      "label": "task",
      "parent": "runSequence_1740422007564_37f7b0cc-812c-42d2-90d1-f10c9b15f967",
      "inputs": [
        5
      ],
      "outputs": "run for sequence: 5",
      "startTime": "2025-02-24T18:33:27.564Z",
      "endTime": "2025-02-24T18:33:27.564Z",
      "duration": 0.0037081241607666016,
      "elapsedTime": "0.004 ms",
      "narratives": [],
      "parallel": false,
      "abstract": false,
      "createTime": "2025-02-24T18:33:27.564Z"
    },
    "group": "nodes"
  },
  {
    "data": {
      "id": "runInDepth_1740422007564_01cc5f8e-a4aa-4283-b9f3-341f1860d9f6",
      "label": "runInDepth",
      "narratives": [],
      "parallel": false,
      "abstract": false,
      "createTime": "2025-02-24T18:33:27.564Z",
      "parent": "runInDepth_1740422007563_3b5c0e86-f548-4ee7-9534-8a0e20137f9f",
      "inputs": [
        [
          "run for sequence: 5",
          "run for sequence: 5",
          "run for sequence: 5",
          "run for sequence: 5",
          "run for sequence: 5",
          "finished runSequenceInDepth for depth : 8"
        ]
      ],
      "outputs": "result1 for run for sequence: 5,run for sequence: 5,run for sequence: 5,run for sequence: 5,run for sequence: 5,finished runSequenceInDepth for depth : 1 at level 10",
      "startTime": "2025-02-24T18:33:27.564Z",
      "endTime": "2025-02-24T18:33:27.565Z",
      "duration": 1.5877079963684082,
      "elapsedTime": "1.588 ms",
      "updateTime": "2025-02-24T18:33:27.565Z"
    },
    "group": "nodes"
  },
  {
    "data": {
      "id": "runSequence_1740422007564_04a518e3-62e9-4649-9de2-c1630dca4f04",
      "label": "runSequence",
      "narratives": [],
      "parallel": false,
      "abstract": false,
      "createTime": "2025-02-24T18:33:27.564Z",
      "parent": "runInDepth_1740422007564_516dfdd7-ffef-47ef-b0e5-c0c2b4cf914e",
      "inputs": [
        6
      ],
      "outputs": [
        "run for sequence: 5",
        "run for sequence: 5",
        "run for sequence: 5",
        "run for sequence: 5",
        "run for sequence: 5",
        "finished runSequenceInDepth for depth : 6"
      ],
      "startTime": "2025-02-24T18:33:27.564Z",
      "endTime": "2025-02-24T18:33:27.564Z",
      "duration": 0.11654186248779297,
      "elapsedTime": "0.117 ms",
      "updateTime": "2025-02-24T18:33:27.564Z"
    },
    "group": "nodes"
  },
  {
    "data": {
      "id": "task_1740422007564_bf41b307-2e4a-4007-9ffc-5d6627f7e492",
      "label": "task",
      "parent": "runSequence_1740422007564_04a518e3-62e9-4649-9de2-c1630dca4f04",
      "inputs": [
        5
      ],
      "outputs": "run for sequence: 5",
      "startTime": "2025-02-24T18:33:27.564Z",
      "endTime": "2025-02-24T18:33:27.564Z",
      "duration": 0.003667116165161133,
      "elapsedTime": "0.004 ms",
      "narratives": [],
      "parallel": false,
      "abstract": false,
      "createTime": "2025-02-24T18:33:27.564Z"
    },
    "group": "nodes"
  },
  {
    "data": {
      "id": "task_1740422007564_69d22b52-d904-4c81-a48c-d14476abbfe5",
      "label": "task",
      "parent": "runSequence_1740422007564_04a518e3-62e9-4649-9de2-c1630dca4f04",
      "inputs": [
        5
      ],
      "outputs": "run for sequence: 5",
      "startTime": "2025-02-24T18:33:27.564Z",
      "endTime": "2025-02-24T18:33:27.564Z",
      "duration": 0.003959178924560547,
      "elapsedTime": "0.004 ms",
      "narratives": [],
      "parallel": false,
      "abstract": false,
      "createTime": "2025-02-24T18:33:27.564Z"
    },
    "group": "nodes"
  },
  {
    "data": {
      "id": "task_1740422007564_6f86d27f-3b76-4336-a01a-57390368590c",
      "label": "task",
      "parent": "runSequence_1740422007564_04a518e3-62e9-4649-9de2-c1630dca4f04",
      "inputs": [
        5
      ],
      "outputs": "run for sequence: 5",
      "startTime": "2025-02-24T18:33:27.564Z",
      "endTime": "2025-02-24T18:33:27.564Z",
      "duration": 0.0036661624908447266,
      "elapsedTime": "0.004 ms",
      "narratives": [],
      "parallel": false,
      "abstract": false,
      "createTime": "2025-02-24T18:33:27.564Z"
    },
    "group": "nodes"
  },
  {
    "data": {
      "id": "task_1740422007564_2caf754f-42d4-4127-a0b9-a3643bfaed87",
      "label": "task",
      "parent": "runSequence_1740422007564_04a518e3-62e9-4649-9de2-c1630dca4f04",
      "inputs": [
        5
      ],
      "outputs": "run for sequence: 5",
      "startTime": "2025-02-24T18:33:27.564Z",
      "endTime": "2025-02-24T18:33:27.564Z",
      "duration": 0.003332853317260742,
      "elapsedTime": "0.003 ms",
      "narratives": [],
      "parallel": false,
      "abstract": false,
      "createTime": "2025-02-24T18:33:27.564Z"
    },
    "group": "nodes"
  },
  {
    "data": {
      "id": "task_1740422007564_73fc3a38-d7c5-4ffe-82c8-da949ef34ab9",
      "label": "task",
      "parent": "runSequence_1740422007564_04a518e3-62e9-4649-9de2-c1630dca4f04",
      "inputs": [
        5
      ],
      "outputs": "run for sequence: 5",
      "startTime": "2025-02-24T18:33:27.564Z",
      "endTime": "2025-02-24T18:33:27.564Z",
      "duration": 0.0034170150756835938,
      "elapsedTime": "0.003 ms",
      "narratives": [],
      "parallel": false,
      "abstract": false,
      "createTime": "2025-02-24T18:33:27.564Z"
    },
    "group": "nodes"
  },
  {
    "data": {
      "id": "runInDepth_1740422007564_516dfdd7-ffef-47ef-b0e5-c0c2b4cf914e",
      "label": "runInDepth",
      "narratives": [],
      "parallel": false,
      "abstract": false,
      "createTime": "2025-02-24T18:33:27.564Z",
      "parent": "runInDepth_1740422007564_01cc5f8e-a4aa-4283-b9f3-341f1860d9f6",
      "inputs": [
        [
          "run for sequence: 5",
          "run for sequence: 5",
          "run for sequence: 5",
          "run for sequence: 5",
          "run for sequence: 5",
          "finished runSequenceInDepth for depth : 7"
        ]
      ],
      "outputs": "result1 for run for sequence: 5,run for sequence: 5,run for sequence: 5,run for sequence: 5,run for sequence: 5,finished runSequenceInDepth for depth : 1 at level 10",
      "startTime": "2025-02-24T18:33:27.564Z",
      "endTime": "2025-02-24T18:33:27.565Z",
      "duration": 1.3659579753875732,
      "elapsedTime": "1.366 ms",
      "updateTime": "2025-02-24T18:33:27.565Z"
    },
    "group": "nodes"
  },
  {
    "data": {
      "id": "runSequence_1740422007564_435a159e-a157-4979-9442-59895408bb95",
      "label": "runSequence",
      "narratives": [],
      "parallel": false,
      "abstract": false,
      "createTime": "2025-02-24T18:33:27.564Z",
      "parent": "runInDepth_1740422007564_8242bbdd-eb4b-4119-a5e8-99c9d56da60a",
      "inputs": [
        5
      ],
      "outputs": [
        "run for sequence: 5",
        "run for sequence: 5",
        "run for sequence: 5",
        "run for sequence: 5",
        "run for sequence: 5",
        "finished runSequenceInDepth for depth : 5"
      ],
      "startTime": "2025-02-24T18:33:27.564Z",
      "endTime": "2025-02-24T18:33:27.564Z",
      "duration": 0.11366701126098633,
      "elapsedTime": "0.114 ms",
      "updateTime": "2025-02-24T18:33:27.564Z"
    },
    "group": "nodes"
  },
  {
    "data": {
      "id": "task_1740422007564_73d8f2cc-21c9-4919-8aeb-da4bcda1a975",
      "label": "task",
      "parent": "runSequence_1740422007564_435a159e-a157-4979-9442-59895408bb95",
      "inputs": [
        5
      ],
      "outputs": "run for sequence: 5",
      "startTime": "2025-02-24T18:33:27.564Z",
      "endTime": "2025-02-24T18:33:27.564Z",
      "duration": 0.003041982650756836,
      "elapsedTime": "0.003 ms",
      "narratives": [],
      "parallel": false,
      "abstract": false,
      "createTime": "2025-02-24T18:33:27.564Z"
    },
    "group": "nodes"
  },
  {
    "data": {
      "id": "task_1740422007564_b1bc9a3f-eb04-4c1a-aeae-dc90aee3ccda",
      "label": "task",
      "parent": "runSequence_1740422007564_435a159e-a157-4979-9442-59895408bb95",
      "inputs": [
        5
      ],
      "outputs": "run for sequence: 5",
      "startTime": "2025-02-24T18:33:27.564Z",
      "endTime": "2025-02-24T18:33:27.564Z",
      "duration": 0.0032498836517333984,
      "elapsedTime": "0.003 ms",
      "narratives": [],
      "parallel": false,
      "abstract": false,
      "createTime": "2025-02-24T18:33:27.564Z"
    },
    "group": "nodes"
  },
  {
    "data": {
      "id": "task_1740422007564_9da417af-f2c2-45b1-8e35-7f3dca5593c1",
      "label": "task",
      "parent": "runSequence_1740422007564_435a159e-a157-4979-9442-59895408bb95",
      "inputs": [
        5
      ],
      "outputs": "run for sequence: 5",
      "startTime": "2025-02-24T18:33:27.564Z",
      "endTime": "2025-02-24T18:33:27.564Z",
      "duration": 0.0032918453216552734,
      "elapsedTime": "0.003 ms",
      "narratives": [],
      "parallel": false,
      "abstract": false,
      "createTime": "2025-02-24T18:33:27.564Z"
    },
    "group": "nodes"
  },
  {
    "data": {
      "id": "task_1740422007564_79f34091-1354-4586-a8d7-42f37ccee090",
      "label": "task",
      "parent": "runSequence_1740422007564_435a159e-a157-4979-9442-59895408bb95",
      "inputs": [
        5
      ],
      "outputs": "run for sequence: 5",
      "startTime": "2025-02-24T18:33:27.564Z",
      "endTime": "2025-02-24T18:33:27.564Z",
      "duration": 0.0033750534057617188,
      "elapsedTime": "0.003 ms",
      "narratives": [],
      "parallel": false,
      "abstract": false,
      "createTime": "2025-02-24T18:33:27.564Z"
    },
    "group": "nodes"
  },
  {
    "data": {
      "id": "task_1740422007564_f1459d0c-7083-4586-99b1-60ba6f31d757",
      "label": "task",
      "parent": "runSequence_1740422007564_435a159e-a157-4979-9442-59895408bb95",
      "inputs": [
        5
      ],
      "outputs": "run for sequence: 5",
      "startTime": "2025-02-24T18:33:27.564Z",
      "endTime": "2025-02-24T18:33:27.564Z",
      "duration": 0.0035419464111328125,
      "elapsedTime": "0.004 ms",
      "narratives": [],
      "parallel": false,
      "abstract": false,
      "createTime": "2025-02-24T18:33:27.564Z"
    },
    "group": "nodes"
  },
  {
    "data": {
      "id": "runInDepth_1740422007564_8242bbdd-eb4b-4119-a5e8-99c9d56da60a",
      "label": "runInDepth",
      "narratives": [],
      "parallel": false,
      "abstract": false,
      "createTime": "2025-02-24T18:33:27.564Z",
      "parent": "runInDepth_1740422007564_516dfdd7-ffef-47ef-b0e5-c0c2b4cf914e",
      "inputs": [
        [
          "run for sequence: 5",
          "run for sequence: 5",
          "run for sequence: 5",
          "run for sequence: 5",
          "run for sequence: 5",
          "finished runSequenceInDepth for depth : 6"
        ]
      ],
      "outputs": "result1 for run for sequence: 5,run for sequence: 5,run for sequence: 5,run for sequence: 5,run for sequence: 5,finished runSequenceInDepth for depth : 1 at level 10",
      "startTime": "2025-02-24T18:33:27.564Z",
      "endTime": "2025-02-24T18:33:27.565Z",
      "duration": 1.1920840740203857,
      "elapsedTime": "1.192 ms",
      "updateTime": "2025-02-24T18:33:27.565Z"
    },
    "group": "nodes"
  },
  {
    "data": {
      "id": "runSequence_1740422007564_3ec8dd2a-9d79-4e6f-b75d-f50ae17dc3b8",
      "label": "runSequence",
      "narratives": [],
      "parallel": false,
      "abstract": false,
      "createTime": "2025-02-24T18:33:27.564Z",
      "parent": "runInDepth_1740422007564_e9574be5-6c13-4e74-814e-594179bf4ea8",
      "inputs": [
        4
      ],
      "outputs": [
        "run for sequence: 5",
        "run for sequence: 5",
        "run for sequence: 5",
        "run for sequence: 5",
        "run for sequence: 5",
        "finished runSequenceInDepth for depth : 4"
      ],
      "startTime": "2025-02-24T18:33:27.564Z",
      "endTime": "2025-02-24T18:33:27.564Z",
      "duration": 0.16750001907348633,
      "elapsedTime": "0.168 ms",
      "updateTime": "2025-02-24T18:33:27.564Z"
    },
    "group": "nodes"
  },
  {
    "data": {
      "id": "task_1740422007564_a085c229-68f4-4a62-aabe-a91f8a625a25",
      "label": "task",
      "parent": "runSequence_1740422007564_3ec8dd2a-9d79-4e6f-b75d-f50ae17dc3b8",
      "inputs": [
        5
      ],
      "outputs": "run for sequence: 5",
      "startTime": "2025-02-24T18:33:27.564Z",
      "endTime": "2025-02-24T18:33:27.564Z",
      "duration": 0.004500150680541992,
      "elapsedTime": "0.005 ms",
      "narratives": [],
      "parallel": false,
      "abstract": false,
      "createTime": "2025-02-24T18:33:27.564Z"
    },
    "group": "nodes"
  },
  {
    "data": {
      "id": "task_1740422007564_6466aa21-4118-431c-a09c-9fbdb334a519",
      "label": "task",
      "parent": "runSequence_1740422007564_3ec8dd2a-9d79-4e6f-b75d-f50ae17dc3b8",
      "inputs": [
        5
      ],
      "outputs": "run for sequence: 5",
      "startTime": "2025-02-24T18:33:27.564Z",
      "endTime": "2025-02-24T18:33:27.564Z",
      "duration": 0.0034999847412109375,
      "elapsedTime": "0.003 ms",
      "narratives": [],
      "parallel": false,
      "abstract": false,
      "createTime": "2025-02-24T18:33:27.564Z"
    },
    "group": "nodes"
  },
  {
    "data": {
      "id": "task_1740422007564_d2d8cec9-aaaa-4557-9cd6-579ae160516d",
      "label": "task",
      "parent": "runSequence_1740422007564_3ec8dd2a-9d79-4e6f-b75d-f50ae17dc3b8",
      "inputs": [
        5
      ],
      "outputs": "run for sequence: 5",
      "startTime": "2025-02-24T18:33:27.564Z",
      "endTime": "2025-02-24T18:33:27.564Z",
      "duration": 0.003374814987182617,
      "elapsedTime": "0.003 ms",
      "narratives": [],
      "parallel": false,
      "abstract": false,
      "createTime": "2025-02-24T18:33:27.564Z"
    },
    "group": "nodes"
  },
  {
    "data": {
      "id": "task_1740422007564_1f4e7052-459d-4d08-9180-963e7ff0fd24",
      "label": "task",
      "parent": "runSequence_1740422007564_3ec8dd2a-9d79-4e6f-b75d-f50ae17dc3b8",
      "inputs": [
        5
      ],
      "outputs": "run for sequence: 5",
      "startTime": "2025-02-24T18:33:27.564Z",
      "endTime": "2025-02-24T18:33:27.564Z",
      "duration": 0.0036668777465820312,
      "elapsedTime": "0.004 ms",
      "narratives": [],
      "parallel": false,
      "abstract": false,
      "createTime": "2025-02-24T18:33:27.564Z"
    },
    "group": "nodes"
  },
  {
    "data": {
      "id": "task_1740422007564_ab9752cf-fbda-4ae4-a13d-80b875b80c57",
      "label": "task",
      "parent": "runSequence_1740422007564_3ec8dd2a-9d79-4e6f-b75d-f50ae17dc3b8",
      "inputs": [
        5
      ],
      "outputs": "run for sequence: 5",
      "startTime": "2025-02-24T18:33:27.564Z",
      "endTime": "2025-02-24T18:33:27.564Z",
      "duration": 0.0033338069915771484,
      "elapsedTime": "0.003 ms",
      "narratives": [],
      "parallel": false,
      "abstract": false,
      "createTime": "2025-02-24T18:33:27.564Z"
    },
    "group": "nodes"
  },
  {
    "data": {
      "id": "runInDepth_1740422007564_e9574be5-6c13-4e74-814e-594179bf4ea8",
      "label": "runInDepth",
      "narratives": [],
      "parallel": false,
      "abstract": false,
      "createTime": "2025-02-24T18:33:27.564Z",
      "parent": "runInDepth_1740422007564_8242bbdd-eb4b-4119-a5e8-99c9d56da60a",
      "inputs": [
        [
          "run for sequence: 5",
          "run for sequence: 5",
          "run for sequence: 5",
          "run for sequence: 5",
          "run for sequence: 5",
          "finished runSequenceInDepth for depth : 5"
        ]
      ],
      "outputs": "result1 for run for sequence: 5,run for sequence: 5,run for sequence: 5,run for sequence: 5,run for sequence: 5,finished runSequenceInDepth for depth : 1 at level 10",
      "startTime": "2025-02-24T18:33:27.564Z",
      "endTime": "2025-02-24T18:33:27.565Z",
      "duration": 0.9771251678466797,
      "elapsedTime": "0.977 ms",
      "updateTime": "2025-02-24T18:33:27.565Z"
    },
    "group": "nodes"
  },
  {
    "data": {
      "id": "runSequence_1740422007564_0ee79e39-5f9f-41aa-80a4-537f449b47c7",
      "label": "runSequence",
      "narratives": [],
      "parallel": false,
      "abstract": false,
      "createTime": "2025-02-24T18:33:27.564Z",
      "parent": "runInDepth_1740422007564_3709665e-ba20-48e5-bdea-02ea83bce351",
      "inputs": [
        3
      ],
      "outputs": [
        "run for sequence: 5",
        "run for sequence: 5",
        "run for sequence: 5",
        "run for sequence: 5",
        "run for sequence: 5",
        "finished runSequenceInDepth for depth : 3"
      ],
      "startTime": "2025-02-24T18:33:27.564Z",
      "endTime": "2025-02-24T18:33:27.564Z",
      "duration": 0.125,
      "elapsedTime": "0.125 ms",
      "updateTime": "2025-02-24T18:33:27.564Z"
    },
    "group": "nodes"
  },
  {
    "data": {
      "id": "task_1740422007564_d8dae6bc-82ea-4139-a88d-655ddc60c498",
      "label": "task",
      "parent": "runSequence_1740422007564_0ee79e39-5f9f-41aa-80a4-537f449b47c7",
      "inputs": [
        5
      ],
      "outputs": "run for sequence: 5",
      "startTime": "2025-02-24T18:33:27.564Z",
      "endTime": "2025-02-24T18:33:27.564Z",
      "duration": 0.002958059310913086,
      "elapsedTime": "0.003 ms",
      "narratives": [],
      "parallel": false,
      "abstract": false,
      "createTime": "2025-02-24T18:33:27.564Z"
    },
    "group": "nodes"
  },
  {
    "data": {
      "id": "task_1740422007564_f78d0150-0c1d-447d-acc0-2430c95dadc8",
      "label": "task",
      "parent": "runSequence_1740422007564_0ee79e39-5f9f-41aa-80a4-537f449b47c7",
      "inputs": [
        5
      ],
      "outputs": "run for sequence: 5",
      "startTime": "2025-02-24T18:33:27.564Z",
      "endTime": "2025-02-24T18:33:27.564Z",
      "duration": 0.0033330917358398438,
      "elapsedTime": "0.003 ms",
      "narratives": [],
      "parallel": false,
      "abstract": false,
      "createTime": "2025-02-24T18:33:27.564Z"
    },
    "group": "nodes"
  },
  {
    "data": {
      "id": "task_1740422007564_59e3359b-3fa7-44e9-8d38-ca20c418decb",
      "label": "task",
      "parent": "runSequence_1740422007564_0ee79e39-5f9f-41aa-80a4-537f449b47c7",
      "inputs": [
        5
      ],
      "outputs": "run for sequence: 5",
      "startTime": "2025-02-24T18:33:27.564Z",
      "endTime": "2025-02-24T18:33:27.564Z",
      "duration": 0.0031671524047851562,
      "elapsedTime": "0.003 ms",
      "narratives": [],
      "parallel": false,
      "abstract": false,
      "createTime": "2025-02-24T18:33:27.564Z"
    },
    "group": "nodes"
  },
  {
    "data": {
      "id": "task_1740422007564_c63a7fac-9ffd-4e8b-be29-361854abe826",
      "label": "task",
      "parent": "runSequence_1740422007564_0ee79e39-5f9f-41aa-80a4-537f449b47c7",
      "inputs": [
        5
      ],
      "outputs": "run for sequence: 5",
      "startTime": "2025-02-24T18:33:27.564Z",
      "endTime": "2025-02-24T18:33:27.564Z",
      "duration": 0.0034160614013671875,
      "elapsedTime": "0.003 ms",
      "narratives": [],
      "parallel": false,
      "abstract": false,
      "createTime": "2025-02-24T18:33:27.564Z"
    },
    "group": "nodes"
  },
  {
    "data": {
      "id": "task_1740422007564_0cb25d6c-2cfe-4c7d-a55f-c19887eadd65",
      "label": "task",
      "parent": "runSequence_1740422007564_0ee79e39-5f9f-41aa-80a4-537f449b47c7",
      "inputs": [
        5
      ],
      "outputs": "run for sequence: 5",
      "startTime": "2025-02-24T18:33:27.564Z",
      "endTime": "2025-02-24T18:33:27.564Z",
      "duration": 0.003292083740234375,
      "elapsedTime": "0.003 ms",
      "narratives": [],
      "parallel": false,
      "abstract": false,
      "createTime": "2025-02-24T18:33:27.564Z"
    },
    "group": "nodes"
  },
  {
    "data": {
      "id": "runInDepth_1740422007564_3709665e-ba20-48e5-bdea-02ea83bce351",
      "label": "runInDepth",
      "narratives": [],
      "parallel": false,
      "abstract": false,
      "createTime": "2025-02-24T18:33:27.564Z",
      "parent": "runInDepth_1740422007564_e9574be5-6c13-4e74-814e-594179bf4ea8",
      "inputs": [
        [
          "run for sequence: 5",
          "run for sequence: 5",
          "run for sequence: 5",
          "run for sequence: 5",
          "run for sequence: 5",
          "finished runSequenceInDepth for depth : 4"
        ]
      ],
      "outputs": "result1 for run for sequence: 5,run for sequence: 5,run for sequence: 5,run for sequence: 5,run for sequence: 5,finished runSequenceInDepth for depth : 1 at level 10",
      "startTime": "2025-02-24T18:33:27.564Z",
      "endTime": "2025-02-24T18:33:27.565Z",
      "duration": 0.7472500801086426,
      "elapsedTime": "0.747 ms",
      "updateTime": "2025-02-24T18:33:27.565Z"
    },
    "group": "nodes"
  },
  {
    "data": {
      "id": "runSequence_1740422007564_8fc8c562-e70f-44bd-a50d-9cc1caf413b4",
      "label": "runSequence",
      "narratives": [],
      "parallel": false,
      "abstract": false,
      "createTime": "2025-02-24T18:33:27.564Z",
      "parent": "runInDepth_1740422007564_566a70b1-6b09-4a1e-9e75-8aed5c44476d",
      "inputs": [
        2
      ],
      "outputs": [
        "run for sequence: 5",
        "run for sequence: 5",
        "run for sequence: 5",
        "run for sequence: 5",
        "run for sequence: 5",
        "finished runSequenceInDepth for depth : 2"
      ],
      "startTime": "2025-02-24T18:33:27.564Z",
      "endTime": "2025-02-24T18:33:27.565Z",
      "duration": 0.14412498474121094,
      "elapsedTime": "0.144 ms",
      "updateTime": "2025-02-24T18:33:27.565Z"
    },
    "group": "nodes"
  },
  {
    "data": {
      "id": "task_1740422007564_9b4d38cb-854f-47e6-adef-dec979734421",
      "label": "task",
      "parent": "runSequence_1740422007564_8fc8c562-e70f-44bd-a50d-9cc1caf413b4",
      "inputs": [
        5
      ],
      "outputs": "run for sequence: 5",
      "startTime": "2025-02-24T18:33:27.564Z",
      "endTime": "2025-02-24T18:33:27.564Z",
      "duration": 0.004999876022338867,
      "elapsedTime": "0.005 ms",
      "narratives": [],
      "parallel": false,
      "abstract": false,
      "createTime": "2025-02-24T18:33:27.564Z"
    },
    "group": "nodes"
  },
  {
    "data": {
      "id": "task_1740422007564_7cab40db-4170-4231-98cb-04aac0cac0c7",
      "label": "task",
      "parent": "runSequence_1740422007564_8fc8c562-e70f-44bd-a50d-9cc1caf413b4",
      "inputs": [
        5
      ],
      "outputs": "run for sequence: 5",
      "startTime": "2025-02-24T18:33:27.565Z",
      "endTime": "2025-02-24T18:33:27.565Z",
      "duration": 0.0033750534057617188,
      "elapsedTime": "0.003 ms",
      "narratives": [],
      "parallel": false,
      "abstract": false,
      "createTime": "2025-02-24T18:33:27.565Z"
    },
    "group": "nodes"
  },
  {
    "data": {
      "id": "task_1740422007565_0e37959c-9e44-473f-979c-27a994386e3d",
      "label": "task",
      "parent": "runSequence_1740422007564_8fc8c562-e70f-44bd-a50d-9cc1caf413b4",
      "inputs": [
        5
      ],
      "outputs": "run for sequence: 5",
      "startTime": "2025-02-24T18:33:27.565Z",
      "endTime": "2025-02-24T18:33:27.565Z",
      "duration": 0.0033750534057617188,
      "elapsedTime": "0.003 ms",
      "narratives": [],
      "parallel": false,
      "abstract": false,
      "createTime": "2025-02-24T18:33:27.565Z"
    },
    "group": "nodes"
  },
  {
    "data": {
      "id": "task_1740422007565_eb6b2875-519d-477f-868c-a3276dda3709",
      "label": "task",
      "parent": "runSequence_1740422007564_8fc8c562-e70f-44bd-a50d-9cc1caf413b4",
      "inputs": [
        5
      ],
      "outputs": "run for sequence: 5",
      "startTime": "2025-02-24T18:33:27.565Z",
      "endTime": "2025-02-24T18:33:27.565Z",
      "duration": 0.0033330917358398438,
      "elapsedTime": "0.003 ms",
      "narratives": [],
      "parallel": false,
      "abstract": false,
      "createTime": "2025-02-24T18:33:27.565Z"
    },
    "group": "nodes"
  },
  {
    "data": {
      "id": "task_1740422007565_acc08589-af83-4aef-85c5-1b66dae6dbba",
      "label": "task",
      "parent": "runSequence_1740422007564_8fc8c562-e70f-44bd-a50d-9cc1caf413b4",
      "inputs": [
        5
      ],
      "outputs": "run for sequence: 5",
      "startTime": "2025-02-24T18:33:27.565Z",
      "endTime": "2025-02-24T18:33:27.565Z",
      "duration": 0.003292083740234375,
      "elapsedTime": "0.003 ms",
      "narratives": [],
      "parallel": false,
      "abstract": false,
      "createTime": "2025-02-24T18:33:27.565Z"
    },
    "group": "nodes"
  },
  {
    "data": {
      "id": "runInDepth_1740422007564_566a70b1-6b09-4a1e-9e75-8aed5c44476d",
      "label": "runInDepth",
      "narratives": [],
      "parallel": false,
      "abstract": false,
      "createTime": "2025-02-24T18:33:27.565Z",
      "parent": "runInDepth_1740422007564_3709665e-ba20-48e5-bdea-02ea83bce351",
      "inputs": [
        [
          "run for sequence: 5",
          "run for sequence: 5",
          "run for sequence: 5",
          "run for sequence: 5",
          "run for sequence: 5",
          "finished runSequenceInDepth for depth : 3"
        ]
      ],
      "outputs": "result1 for run for sequence: 5,run for sequence: 5,run for sequence: 5,run for sequence: 5,run for sequence: 5,finished runSequenceInDepth for depth : 1 at level 10",
      "startTime": "2025-02-24T18:33:27.564Z",
      "endTime": "2025-02-24T18:33:27.565Z",
      "duration": 0.569666862487793,
      "elapsedTime": "0.570 ms",
      "updateTime": "2025-02-24T18:33:27.565Z"
    },
    "group": "nodes"
  },
  {
    "data": {
      "id": "runSequence_1740422007565_eaacf6b8-6420-4671-83f8-82acc73812a0",
      "label": "runSequence",
      "narratives": [],
      "parallel": false,
      "abstract": false,
      "createTime": "2025-02-24T18:33:27.565Z",
      "parent": "runInDepth_1740422007565_fc105f1b-e37f-4710-b7cb-f1f67e406609",
      "inputs": [
        1
      ],
      "outputs": [
        "run for sequence: 5",
        "run for sequence: 5",
        "run for sequence: 5",
        "run for sequence: 5",
        "run for sequence: 5",
        "finished runSequenceInDepth for depth : 1"
      ],
      "startTime": "2025-02-24T18:33:27.565Z",
      "endTime": "2025-02-24T18:33:27.565Z",
      "duration": 0.14933300018310547,
      "elapsedTime": "0.149 ms",
      "updateTime": "2025-02-24T18:33:27.565Z"
    },
    "group": "nodes"
  },
  {
    "data": {
      "id": "task_1740422007565_57b6d265-4492-427d-b55f-4670984d11e2",
      "label": "task",
      "parent": "runSequence_1740422007565_eaacf6b8-6420-4671-83f8-82acc73812a0",
      "inputs": [
        5
      ],
      "outputs": "run for sequence: 5",
      "startTime": "2025-02-24T18:33:27.565Z",
      "endTime": "2025-02-24T18:33:27.565Z",
      "duration": 0.0053751468658447266,
      "elapsedTime": "0.005 ms",
      "narratives": [],
      "parallel": false,
      "abstract": false,
      "createTime": "2025-02-24T18:33:27.565Z"
    },
    "group": "nodes"
  },
  {
    "data": {
      "id": "task_1740422007565_b787c224-40c0-4825-a4fa-6a4b1ed4ec99",
      "label": "task",
      "parent": "runSequence_1740422007565_eaacf6b8-6420-4671-83f8-82acc73812a0",
      "inputs": [
        5
      ],
      "outputs": "run for sequence: 5",
      "startTime": "2025-02-24T18:33:27.565Z",
      "endTime": "2025-02-24T18:33:27.565Z",
      "duration": 0.0034170150756835938,
      "elapsedTime": "0.003 ms",
      "narratives": [],
      "parallel": false,
      "abstract": false,
      "createTime": "2025-02-24T18:33:27.565Z"
    },
    "group": "nodes"
  },
  {
    "data": {
      "id": "task_1740422007565_e3ca23f1-dfe2-4910-bc31-3ad350089394",
      "label": "task",
      "parent": "runSequence_1740422007565_eaacf6b8-6420-4671-83f8-82acc73812a0",
      "inputs": [
        5
      ],
      "outputs": "run for sequence: 5",
      "startTime": "2025-02-24T18:33:27.565Z",
      "endTime": "2025-02-24T18:33:27.565Z",
      "duration": 0.0034170150756835938,
      "elapsedTime": "0.003 ms",
      "narratives": [],
      "parallel": false,
      "abstract": false,
      "createTime": "2025-02-24T18:33:27.565Z"
    },
    "group": "nodes"
  },
  {
    "data": {
      "id": "task_1740422007565_cbabe7cd-0c21-4123-b90f-b1efa5c96532",
      "label": "task",
      "parent": "runSequence_1740422007565_eaacf6b8-6420-4671-83f8-82acc73812a0",
      "inputs": [
        5
      ],
      "outputs": "run for sequence: 5",
      "startTime": "2025-02-24T18:33:27.565Z",
      "endTime": "2025-02-24T18:33:27.565Z",
      "duration": 0.0032501220703125,
      "elapsedTime": "0.003 ms",
      "narratives": [],
      "parallel": false,
      "abstract": false,
      "createTime": "2025-02-24T18:33:27.565Z"
    },
    "group": "nodes"
  },
  {
    "data": {
      "id": "task_1740422007565_a14729da-b9ee-4f82-aca7-4bcb8c9a88bf",
      "label": "task",
      "parent": "runSequence_1740422007565_eaacf6b8-6420-4671-83f8-82acc73812a0",
      "inputs": [
        5
      ],
      "outputs": "run for sequence: 5",
      "startTime": "2025-02-24T18:33:27.565Z",
      "endTime": "2025-02-24T18:33:27.565Z",
      "duration": 0.0035829544067382812,
      "elapsedTime": "0.004 ms",
      "narratives": [],
      "parallel": false,
      "abstract": false,
      "createTime": "2025-02-24T18:33:27.565Z"
    },
    "group": "nodes"
  },
  {
    "data": {
      "id": "runInDepth_1740422007565_fc105f1b-e37f-4710-b7cb-f1f67e406609",
      "label": "runInDepth",
      "narratives": [],
      "parallel": false,
      "abstract": false,
      "createTime": "2025-02-24T18:33:27.565Z",
      "parent": "runInDepth_1740422007564_566a70b1-6b09-4a1e-9e75-8aed5c44476d",
      "inputs": [
        [
          "run for sequence: 5",
          "run for sequence: 5",
          "run for sequence: 5",
          "run for sequence: 5",
          "run for sequence: 5",
          "finished runSequenceInDepth for depth : 2"
        ]
      ],
      "outputs": "result1 for run for sequence: 5,run for sequence: 5,run for sequence: 5,run for sequence: 5,run for sequence: 5,finished runSequenceInDepth for depth : 1 at level 10",
      "startTime": "2025-02-24T18:33:27.565Z",
      "endTime": "2025-02-24T18:33:27.565Z",
      "duration": 0.370499849319458,
      "elapsedTime": "0.370 ms",
      "updateTime": "2025-02-24T18:33:27.565Z"
    },
    "group": "nodes"
  },
  {
    "data": {
      "id": "runSequence_1740422007565_c9046c4b-f253-4b99-945f-70883e2ddcd4",
      "label": "runSequence",
      "narratives": [],
      "parallel": false,
      "abstract": false,
      "createTime": "2025-02-24T18:33:27.565Z",
      "parent": "runInDepth_1740422007565_4669d06b-3d78-431e-97e7-99e2f54b6953",
      "inputs": [
        0
      ],
      "outputs": [
        "run for sequence: 5",
        "run for sequence: 5",
        "run for sequence: 5",
        "run for sequence: 5",
        "run for sequence: 5",
        "finished runSequenceInDepth for depth : 0"
      ],
      "startTime": "2025-02-24T18:33:27.565Z",
      "endTime": "2025-02-24T18:33:27.565Z",
      "duration": 0.13191604614257812,
      "elapsedTime": "0.132 ms",
      "updateTime": "2025-02-24T18:33:27.565Z"
    },
    "group": "nodes"
  },
  {
    "data": {
      "id": "task_1740422007565_97f30296-3fb7-4cb5-9ab3-230514059fd6",
      "label": "task",
      "parent": "runSequence_1740422007565_c9046c4b-f253-4b99-945f-70883e2ddcd4",
      "inputs": [
        5
      ],
      "outputs": "run for sequence: 5",
      "startTime": "2025-02-24T18:33:27.565Z",
      "endTime": "2025-02-24T18:33:27.565Z",
      "duration": 0.002875089645385742,
      "elapsedTime": "0.003 ms",
      "narratives": [],
      "parallel": false,
      "abstract": false,
      "createTime": "2025-02-24T18:33:27.565Z"
    },
    "group": "nodes"
  },
  {
    "data": {
      "id": "task_1740422007565_7f5d2423-5460-4417-a603-080e9b1fc309",
      "label": "task",
      "parent": "runSequence_1740422007565_c9046c4b-f253-4b99-945f-70883e2ddcd4",
      "inputs": [
        5
      ],
      "outputs": "run for sequence: 5",
      "startTime": "2025-02-24T18:33:27.565Z",
      "endTime": "2025-02-24T18:33:27.565Z",
      "duration": 0.003332853317260742,
      "elapsedTime": "0.003 ms",
      "narratives": [],
      "parallel": false,
      "abstract": false,
      "createTime": "2025-02-24T18:33:27.565Z"
    },
    "group": "nodes"
  },
  {
    "data": {
      "id": "task_1740422007565_ac64e2ef-6583-424f-ae49-38413e287f7b",
      "label": "task",
      "parent": "runSequence_1740422007565_c9046c4b-f253-4b99-945f-70883e2ddcd4",
      "inputs": [
        5
      ],
      "outputs": "run for sequence: 5",
      "startTime": "2025-02-24T18:33:27.565Z",
      "endTime": "2025-02-24T18:33:27.565Z",
      "duration": 0.003290891647338867,
      "elapsedTime": "0.003 ms",
      "narratives": [],
      "parallel": false,
      "abstract": false,
      "createTime": "2025-02-24T18:33:27.565Z"
    },
    "group": "nodes"
  },
  {
    "data": {
      "id": "task_1740422007565_b900f6d4-564b-4354-9872-001a31882cfa",
      "label": "task",
      "parent": "runSequence_1740422007565_c9046c4b-f253-4b99-945f-70883e2ddcd4",
      "inputs": [
        5
      ],
      "outputs": "run for sequence: 5",
      "startTime": "2025-02-24T18:33:27.565Z",
      "endTime": "2025-02-24T18:33:27.565Z",
      "duration": 0.0034170150756835938,
      "elapsedTime": "0.003 ms",
      "narratives": [],
      "parallel": false,
      "abstract": false,
      "createTime": "2025-02-24T18:33:27.565Z"
    },
    "group": "nodes"
  },
  {
    "data": {
      "id": "task_1740422007565_74169c2a-0426-4665-9045-a9eb0e0bc9a8",
      "label": "task",
      "parent": "runSequence_1740422007565_c9046c4b-f253-4b99-945f-70883e2ddcd4",
      "inputs": [
        5
      ],
      "outputs": "run for sequence: 5",
      "startTime": "2025-02-24T18:33:27.565Z",
      "endTime": "2025-02-24T18:33:27.565Z",
      "duration": 0.003415822982788086,
      "elapsedTime": "0.003 ms",
      "narratives": [],
      "parallel": false,
      "abstract": false,
      "createTime": "2025-02-24T18:33:27.565Z"
    },
    "group": "nodes"
  },
  {
    "data": {
      "id": "runInDepth_1740422007565_4669d06b-3d78-431e-97e7-99e2f54b6953",
      "label": "runInDepth",
      "narratives": [],
      "parallel": false,
      "abstract": false,
      "createTime": "2025-02-24T18:33:27.565Z",
      "parent": "runInDepth_1740422007565_fc105f1b-e37f-4710-b7cb-f1f67e406609",
      "inputs": [
        [
          "run for sequence: 5",
          "run for sequence: 5",
          "run for sequence: 5",
          "run for sequence: 5",
          "run for sequence: 5",
          "finished runSequenceInDepth for depth : 1"
        ]
      ],
      "outputs": "result1 for run for sequence: 5,run for sequence: 5,run for sequence: 5,run for sequence: 5,run for sequence: 5,finished runSequenceInDepth for depth : 1 at level 10",
      "startTime": "2025-02-24T18:33:27.565Z",
      "endTime": "2025-02-24T18:33:27.565Z",
      "duration": 0.16316699981689453,
      "elapsedTime": "0.163 ms",
      "updateTime": "2025-02-24T18:33:27.565Z"
    },
    "group": "nodes"
  },
  {
    "data": {
      "id": "task_1740422007562_b849d372-f07c-4a21-b478-36d083cc056c->task_1740422007562_d572a969-ebcb-44ae-9a72-48aeffe9b0e2",
      "source": "task_1740422007562_b849d372-f07c-4a21-b478-36d083cc056c",
      "target": "task_1740422007562_d572a969-ebcb-44ae-9a72-48aeffe9b0e2",
      "parent": "runSequence_1740422007562_357a4cc1-104b-4744-ab37-bd283b198067",
      "parallel": false
    },
    "group": "edges"
  },
  {
    "data": {
      "id": "task_1740422007562_d572a969-ebcb-44ae-9a72-48aeffe9b0e2->task_1740422007563_33003fe3-051a-4377-bec3-f9f4d96244ca",
      "source": "task_1740422007562_d572a969-ebcb-44ae-9a72-48aeffe9b0e2",
      "target": "task_1740422007563_33003fe3-051a-4377-bec3-f9f4d96244ca",
      "parent": "runSequence_1740422007562_357a4cc1-104b-4744-ab37-bd283b198067",
      "parallel": false
    },
    "group": "edges"
  },
  {
    "data": {
      "id": "task_1740422007563_33003fe3-051a-4377-bec3-f9f4d96244ca->task_1740422007563_de6de59d-0b63-4671-9052-3225cd30cefd",
      "source": "task_1740422007563_33003fe3-051a-4377-bec3-f9f4d96244ca",
      "target": "task_1740422007563_de6de59d-0b63-4671-9052-3225cd30cefd",
      "parent": "runSequence_1740422007562_357a4cc1-104b-4744-ab37-bd283b198067",
      "parallel": false
    },
    "group": "edges"
  },
  {
    "data": {
      "id": "task_1740422007563_de6de59d-0b63-4671-9052-3225cd30cefd->task_1740422007563_7a7d8067-9f95-4042-8b9d-20a0d7d26dd3",
      "source": "task_1740422007563_de6de59d-0b63-4671-9052-3225cd30cefd",
      "target": "task_1740422007563_7a7d8067-9f95-4042-8b9d-20a0d7d26dd3",
      "parent": "runSequence_1740422007562_357a4cc1-104b-4744-ab37-bd283b198067",
      "parallel": false
    },
    "group": "edges"
  },
  {
    "data": {
      "id": "task_1740422007563_633d000c-0d05-4307-a694-d62495e319da->task_1740422007563_fe514b76-670a-424a-8d10-3f632cb66562",
      "source": "task_1740422007563_633d000c-0d05-4307-a694-d62495e319da",
      "target": "task_1740422007563_fe514b76-670a-424a-8d10-3f632cb66562",
      "parent": "runSequence_1740422007563_c5c6bda0-011f-48fe-a6dd-4441b949247d",
      "parallel": false
    },
    "group": "edges"
  },
  {
    "data": {
      "id": "task_1740422007563_fe514b76-670a-424a-8d10-3f632cb66562->task_1740422007563_83007135-966a-406c-af8a-b7e80818d168",
      "source": "task_1740422007563_fe514b76-670a-424a-8d10-3f632cb66562",
      "target": "task_1740422007563_83007135-966a-406c-af8a-b7e80818d168",
      "parent": "runSequence_1740422007563_c5c6bda0-011f-48fe-a6dd-4441b949247d",
      "parallel": false
    },
    "group": "edges"
  },
  {
    "data": {
      "id": "task_1740422007563_83007135-966a-406c-af8a-b7e80818d168->task_1740422007563_fe0224ae-d66e-46f8-82ec-9aaac4067024",
      "source": "task_1740422007563_83007135-966a-406c-af8a-b7e80818d168",
      "target": "task_1740422007563_fe0224ae-d66e-46f8-82ec-9aaac4067024",
      "parent": "runSequence_1740422007563_c5c6bda0-011f-48fe-a6dd-4441b949247d",
      "parallel": false
    },
    "group": "edges"
  },
  {
    "data": {
      "id": "task_1740422007563_fe0224ae-d66e-46f8-82ec-9aaac4067024->task_1740422007563_22baedef-1fb7-40df-97e8-ed434533f8f2",
      "source": "task_1740422007563_fe0224ae-d66e-46f8-82ec-9aaac4067024",
      "target": "task_1740422007563_22baedef-1fb7-40df-97e8-ed434533f8f2",
      "parent": "runSequence_1740422007563_c5c6bda0-011f-48fe-a6dd-4441b949247d",
      "parallel": false
    },
    "group": "edges"
  },
  {
    "data": {
      "id": "task_1740422007563_bbc6d69f-4e62-44d5-8418-2abfec07ee62->task_1740422007563_6a91561a-ec41-41d0-b7b2-7b1fbfe16b94",
      "source": "task_1740422007563_bbc6d69f-4e62-44d5-8418-2abfec07ee62",
      "target": "task_1740422007563_6a91561a-ec41-41d0-b7b2-7b1fbfe16b94",
      "parent": "runSequence_1740422007563_b7242f4b-2356-4e8f-820b-70ee024b3880",
      "parallel": false
    },
    "group": "edges"
  },
  {
    "data": {
      "id": "task_1740422007563_6a91561a-ec41-41d0-b7b2-7b1fbfe16b94->task_1740422007563_e80c31ae-92c0-4863-aed3-08f97c03e248",
      "source": "task_1740422007563_6a91561a-ec41-41d0-b7b2-7b1fbfe16b94",
      "target": "task_1740422007563_e80c31ae-92c0-4863-aed3-08f97c03e248",
      "parent": "runSequence_1740422007563_b7242f4b-2356-4e8f-820b-70ee024b3880",
      "parallel": false
    },
    "group": "edges"
  },
  {
    "data": {
      "id": "task_1740422007563_e80c31ae-92c0-4863-aed3-08f97c03e248->task_1740422007563_a75822e7-f82d-4dba-b846-1c010135cd7d",
      "source": "task_1740422007563_e80c31ae-92c0-4863-aed3-08f97c03e248",
      "target": "task_1740422007563_a75822e7-f82d-4dba-b846-1c010135cd7d",
      "parent": "runSequence_1740422007563_b7242f4b-2356-4e8f-820b-70ee024b3880",
      "parallel": false
    },
    "group": "edges"
  },
  {
    "data": {
      "id": "task_1740422007563_a75822e7-f82d-4dba-b846-1c010135cd7d->task_1740422007563_d91200d3-e548-4023-8e0f-8f8023e1e0f7",
      "source": "task_1740422007563_a75822e7-f82d-4dba-b846-1c010135cd7d",
      "target": "task_1740422007563_d91200d3-e548-4023-8e0f-8f8023e1e0f7",
      "parent": "runSequence_1740422007563_b7242f4b-2356-4e8f-820b-70ee024b3880",
      "parallel": false
    },
    "group": "edges"
  },
  {
    "data": {
      "id": "task_1740422007564_19b9d44a-ce12-47a8-93eb-8035a685356f->task_1740422007564_0ed8549c-6d69-4343-866a-334a8689eb7c",
      "source": "task_1740422007564_19b9d44a-ce12-47a8-93eb-8035a685356f",
      "target": "task_1740422007564_0ed8549c-6d69-4343-866a-334a8689eb7c",
      "parent": "runSequence_1740422007564_37f7b0cc-812c-42d2-90d1-f10c9b15f967",
      "parallel": false
    },
    "group": "edges"
  },
  {
    "data": {
      "id": "task_1740422007564_0ed8549c-6d69-4343-866a-334a8689eb7c->task_1740422007564_d27bb713-700f-4e36-9512-0ae06cd31c8b",
      "source": "task_1740422007564_0ed8549c-6d69-4343-866a-334a8689eb7c",
      "target": "task_1740422007564_d27bb713-700f-4e36-9512-0ae06cd31c8b",
      "parent": "runSequence_1740422007564_37f7b0cc-812c-42d2-90d1-f10c9b15f967",
      "parallel": false
    },
    "group": "edges"
  },
  {
    "data": {
      "id": "task_1740422007564_d27bb713-700f-4e36-9512-0ae06cd31c8b->task_1740422007564_b5869e87-f4a8-497e-8b85-a9a558b2979f",
      "source": "task_1740422007564_d27bb713-700f-4e36-9512-0ae06cd31c8b",
      "target": "task_1740422007564_b5869e87-f4a8-497e-8b85-a9a558b2979f",
      "parent": "runSequence_1740422007564_37f7b0cc-812c-42d2-90d1-f10c9b15f967",
      "parallel": false
    },
    "group": "edges"
  },
  {
    "data": {
      "id": "task_1740422007564_b5869e87-f4a8-497e-8b85-a9a558b2979f->task_1740422007564_3e836c79-df37-4872-93a2-04a2c0c690f4",
      "source": "task_1740422007564_b5869e87-f4a8-497e-8b85-a9a558b2979f",
      "target": "task_1740422007564_3e836c79-df37-4872-93a2-04a2c0c690f4",
      "parent": "runSequence_1740422007564_37f7b0cc-812c-42d2-90d1-f10c9b15f967",
      "parallel": false
    },
    "group": "edges"
  },
  {
    "data": {
      "id": "task_1740422007564_bf41b307-2e4a-4007-9ffc-5d6627f7e492->task_1740422007564_69d22b52-d904-4c81-a48c-d14476abbfe5",
      "source": "task_1740422007564_bf41b307-2e4a-4007-9ffc-5d6627f7e492",
      "target": "task_1740422007564_69d22b52-d904-4c81-a48c-d14476abbfe5",
      "parent": "runSequence_1740422007564_04a518e3-62e9-4649-9de2-c1630dca4f04",
      "parallel": false
    },
    "group": "edges"
  },
  {
    "data": {
      "id": "task_1740422007564_69d22b52-d904-4c81-a48c-d14476abbfe5->task_1740422007564_6f86d27f-3b76-4336-a01a-57390368590c",
      "source": "task_1740422007564_69d22b52-d904-4c81-a48c-d14476abbfe5",
      "target": "task_1740422007564_6f86d27f-3b76-4336-a01a-57390368590c",
      "parent": "runSequence_1740422007564_04a518e3-62e9-4649-9de2-c1630dca4f04",
      "parallel": false
    },
    "group": "edges"
  },
  {
    "data": {
      "id": "task_1740422007564_6f86d27f-3b76-4336-a01a-57390368590c->task_1740422007564_2caf754f-42d4-4127-a0b9-a3643bfaed87",
      "source": "task_1740422007564_6f86d27f-3b76-4336-a01a-57390368590c",
      "target": "task_1740422007564_2caf754f-42d4-4127-a0b9-a3643bfaed87",
      "parent": "runSequence_1740422007564_04a518e3-62e9-4649-9de2-c1630dca4f04",
      "parallel": false
    },
    "group": "edges"
  },
  {
    "data": {
      "id": "task_1740422007564_2caf754f-42d4-4127-a0b9-a3643bfaed87->task_1740422007564_73fc3a38-d7c5-4ffe-82c8-da949ef34ab9",
      "source": "task_1740422007564_2caf754f-42d4-4127-a0b9-a3643bfaed87",
      "target": "task_1740422007564_73fc3a38-d7c5-4ffe-82c8-da949ef34ab9",
      "parent": "runSequence_1740422007564_04a518e3-62e9-4649-9de2-c1630dca4f04",
      "parallel": false
    },
    "group": "edges"
  },
  {
    "data": {
      "id": "task_1740422007564_73d8f2cc-21c9-4919-8aeb-da4bcda1a975->task_1740422007564_b1bc9a3f-eb04-4c1a-aeae-dc90aee3ccda",
      "source": "task_1740422007564_73d8f2cc-21c9-4919-8aeb-da4bcda1a975",
      "target": "task_1740422007564_b1bc9a3f-eb04-4c1a-aeae-dc90aee3ccda",
      "parent": "runSequence_1740422007564_435a159e-a157-4979-9442-59895408bb95",
      "parallel": false
    },
    "group": "edges"
  },
  {
    "data": {
      "id": "task_1740422007564_b1bc9a3f-eb04-4c1a-aeae-dc90aee3ccda->task_1740422007564_9da417af-f2c2-45b1-8e35-7f3dca5593c1",
      "source": "task_1740422007564_b1bc9a3f-eb04-4c1a-aeae-dc90aee3ccda",
      "target": "task_1740422007564_9da417af-f2c2-45b1-8e35-7f3dca5593c1",
      "parent": "runSequence_1740422007564_435a159e-a157-4979-9442-59895408bb95",
      "parallel": false
    },
    "group": "edges"
  },
  {
    "data": {
      "id": "task_1740422007564_9da417af-f2c2-45b1-8e35-7f3dca5593c1->task_1740422007564_79f34091-1354-4586-a8d7-42f37ccee090",
      "source": "task_1740422007564_9da417af-f2c2-45b1-8e35-7f3dca5593c1",
      "target": "task_1740422007564_79f34091-1354-4586-a8d7-42f37ccee090",
      "parent": "runSequence_1740422007564_435a159e-a157-4979-9442-59895408bb95",
      "parallel": false
    },
    "group": "edges"
  },
  {
    "data": {
      "id": "task_1740422007564_79f34091-1354-4586-a8d7-42f37ccee090->task_1740422007564_f1459d0c-7083-4586-99b1-60ba6f31d757",
      "source": "task_1740422007564_79f34091-1354-4586-a8d7-42f37ccee090",
      "target": "task_1740422007564_f1459d0c-7083-4586-99b1-60ba6f31d757",
      "parent": "runSequence_1740422007564_435a159e-a157-4979-9442-59895408bb95",
      "parallel": false
    },
    "group": "edges"
  },
  {
    "data": {
      "id": "task_1740422007564_a085c229-68f4-4a62-aabe-a91f8a625a25->task_1740422007564_6466aa21-4118-431c-a09c-9fbdb334a519",
      "source": "task_1740422007564_a085c229-68f4-4a62-aabe-a91f8a625a25",
      "target": "task_1740422007564_6466aa21-4118-431c-a09c-9fbdb334a519",
      "parent": "runSequence_1740422007564_3ec8dd2a-9d79-4e6f-b75d-f50ae17dc3b8",
      "parallel": false
    },
    "group": "edges"
  },
  {
    "data": {
      "id": "task_1740422007564_6466aa21-4118-431c-a09c-9fbdb334a519->task_1740422007564_d2d8cec9-aaaa-4557-9cd6-579ae160516d",
      "source": "task_1740422007564_6466aa21-4118-431c-a09c-9fbdb334a519",
      "target": "task_1740422007564_d2d8cec9-aaaa-4557-9cd6-579ae160516d",
      "parent": "runSequence_1740422007564_3ec8dd2a-9d79-4e6f-b75d-f50ae17dc3b8",
      "parallel": false
    },
    "group": "edges"
  },
  {
    "data": {
      "id": "task_1740422007564_d2d8cec9-aaaa-4557-9cd6-579ae160516d->task_1740422007564_1f4e7052-459d-4d08-9180-963e7ff0fd24",
      "source": "task_1740422007564_d2d8cec9-aaaa-4557-9cd6-579ae160516d",
      "target": "task_1740422007564_1f4e7052-459d-4d08-9180-963e7ff0fd24",
      "parent": "runSequence_1740422007564_3ec8dd2a-9d79-4e6f-b75d-f50ae17dc3b8",
      "parallel": false
    },
    "group": "edges"
  },
  {
    "data": {
      "id": "task_1740422007564_1f4e7052-459d-4d08-9180-963e7ff0fd24->task_1740422007564_ab9752cf-fbda-4ae4-a13d-80b875b80c57",
      "source": "task_1740422007564_1f4e7052-459d-4d08-9180-963e7ff0fd24",
      "target": "task_1740422007564_ab9752cf-fbda-4ae4-a13d-80b875b80c57",
      "parent": "runSequence_1740422007564_3ec8dd2a-9d79-4e6f-b75d-f50ae17dc3b8",
      "parallel": false
    },
    "group": "edges"
  },
  {
    "data": {
      "id": "task_1740422007564_d8dae6bc-82ea-4139-a88d-655ddc60c498->task_1740422007564_f78d0150-0c1d-447d-acc0-2430c95dadc8",
      "source": "task_1740422007564_d8dae6bc-82ea-4139-a88d-655ddc60c498",
      "target": "task_1740422007564_f78d0150-0c1d-447d-acc0-2430c95dadc8",
      "parent": "runSequence_1740422007564_0ee79e39-5f9f-41aa-80a4-537f449b47c7",
      "parallel": false
    },
    "group": "edges"
  },
  {
    "data": {
      "id": "task_1740422007564_f78d0150-0c1d-447d-acc0-2430c95dadc8->task_1740422007564_59e3359b-3fa7-44e9-8d38-ca20c418decb",
      "source": "task_1740422007564_f78d0150-0c1d-447d-acc0-2430c95dadc8",
      "target": "task_1740422007564_59e3359b-3fa7-44e9-8d38-ca20c418decb",
      "parent": "runSequence_1740422007564_0ee79e39-5f9f-41aa-80a4-537f449b47c7",
      "parallel": false
    },
    "group": "edges"
  },
  {
    "data": {
      "id": "task_1740422007564_59e3359b-3fa7-44e9-8d38-ca20c418decb->task_1740422007564_c63a7fac-9ffd-4e8b-be29-361854abe826",
      "source": "task_1740422007564_59e3359b-3fa7-44e9-8d38-ca20c418decb",
      "target": "task_1740422007564_c63a7fac-9ffd-4e8b-be29-361854abe826",
      "parent": "runSequence_1740422007564_0ee79e39-5f9f-41aa-80a4-537f449b47c7",
      "parallel": false
    },
    "group": "edges"
  },
  {
    "data": {
      "id": "task_1740422007564_c63a7fac-9ffd-4e8b-be29-361854abe826->task_1740422007564_0cb25d6c-2cfe-4c7d-a55f-c19887eadd65",
      "source": "task_1740422007564_c63a7fac-9ffd-4e8b-be29-361854abe826",
      "target": "task_1740422007564_0cb25d6c-2cfe-4c7d-a55f-c19887eadd65",
      "parent": "runSequence_1740422007564_0ee79e39-5f9f-41aa-80a4-537f449b47c7",
      "parallel": false
    },
    "group": "edges"
  },
  {
    "data": {
      "id": "task_1740422007564_9b4d38cb-854f-47e6-adef-dec979734421->task_1740422007564_7cab40db-4170-4231-98cb-04aac0cac0c7",
      "source": "task_1740422007564_9b4d38cb-854f-47e6-adef-dec979734421",
      "target": "task_1740422007564_7cab40db-4170-4231-98cb-04aac0cac0c7",
      "parent": "runSequence_1740422007564_8fc8c562-e70f-44bd-a50d-9cc1caf413b4",
      "parallel": false
    },
    "group": "edges"
  },
  {
    "data": {
      "id": "task_1740422007564_7cab40db-4170-4231-98cb-04aac0cac0c7->task_1740422007565_0e37959c-9e44-473f-979c-27a994386e3d",
      "source": "task_1740422007564_7cab40db-4170-4231-98cb-04aac0cac0c7",
      "target": "task_1740422007565_0e37959c-9e44-473f-979c-27a994386e3d",
      "parent": "runSequence_1740422007564_8fc8c562-e70f-44bd-a50d-9cc1caf413b4",
      "parallel": false
    },
    "group": "edges"
  },
  {
    "data": {
      "id": "task_1740422007565_0e37959c-9e44-473f-979c-27a994386e3d->task_1740422007565_eb6b2875-519d-477f-868c-a3276dda3709",
      "source": "task_1740422007565_0e37959c-9e44-473f-979c-27a994386e3d",
      "target": "task_1740422007565_eb6b2875-519d-477f-868c-a3276dda3709",
      "parent": "runSequence_1740422007564_8fc8c562-e70f-44bd-a50d-9cc1caf413b4",
      "parallel": false
    },
    "group": "edges"
  },
  {
    "data": {
      "id": "task_1740422007565_eb6b2875-519d-477f-868c-a3276dda3709->task_1740422007565_acc08589-af83-4aef-85c5-1b66dae6dbba",
      "source": "task_1740422007565_eb6b2875-519d-477f-868c-a3276dda3709",
      "target": "task_1740422007565_acc08589-af83-4aef-85c5-1b66dae6dbba",
      "parent": "runSequence_1740422007564_8fc8c562-e70f-44bd-a50d-9cc1caf413b4",
      "parallel": false
    },
    "group": "edges"
  },
  {
    "data": {
      "id": "task_1740422007565_57b6d265-4492-427d-b55f-4670984d11e2->task_1740422007565_b787c224-40c0-4825-a4fa-6a4b1ed4ec99",
      "source": "task_1740422007565_57b6d265-4492-427d-b55f-4670984d11e2",
      "target": "task_1740422007565_b787c224-40c0-4825-a4fa-6a4b1ed4ec99",
      "parent": "runSequence_1740422007565_eaacf6b8-6420-4671-83f8-82acc73812a0",
      "parallel": false
    },
    "group": "edges"
  },
  {
    "data": {
      "id": "task_1740422007565_b787c224-40c0-4825-a4fa-6a4b1ed4ec99->task_1740422007565_e3ca23f1-dfe2-4910-bc31-3ad350089394",
      "source": "task_1740422007565_b787c224-40c0-4825-a4fa-6a4b1ed4ec99",
      "target": "task_1740422007565_e3ca23f1-dfe2-4910-bc31-3ad350089394",
      "parent": "runSequence_1740422007565_eaacf6b8-6420-4671-83f8-82acc73812a0",
      "parallel": false
    },
    "group": "edges"
  },
  {
    "data": {
      "id": "task_1740422007565_e3ca23f1-dfe2-4910-bc31-3ad350089394->task_1740422007565_cbabe7cd-0c21-4123-b90f-b1efa5c96532",
      "source": "task_1740422007565_e3ca23f1-dfe2-4910-bc31-3ad350089394",
      "target": "task_1740422007565_cbabe7cd-0c21-4123-b90f-b1efa5c96532",
      "parent": "runSequence_1740422007565_eaacf6b8-6420-4671-83f8-82acc73812a0",
      "parallel": false
    },
    "group": "edges"
  },
  {
    "data": {
      "id": "task_1740422007565_cbabe7cd-0c21-4123-b90f-b1efa5c96532->task_1740422007565_a14729da-b9ee-4f82-aca7-4bcb8c9a88bf",
      "source": "task_1740422007565_cbabe7cd-0c21-4123-b90f-b1efa5c96532",
      "target": "task_1740422007565_a14729da-b9ee-4f82-aca7-4bcb8c9a88bf",
      "parent": "runSequence_1740422007565_eaacf6b8-6420-4671-83f8-82acc73812a0",
      "parallel": false
    },
    "group": "edges"
  },
  {
    "data": {
      "id": "task_1740422007565_97f30296-3fb7-4cb5-9ab3-230514059fd6->task_1740422007565_7f5d2423-5460-4417-a603-080e9b1fc309",
      "source": "task_1740422007565_97f30296-3fb7-4cb5-9ab3-230514059fd6",
      "target": "task_1740422007565_7f5d2423-5460-4417-a603-080e9b1fc309",
      "parent": "runSequence_1740422007565_c9046c4b-f253-4b99-945f-70883e2ddcd4",
      "parallel": false
    },
    "group": "edges"
  },
  {
    "data": {
      "id": "task_1740422007565_7f5d2423-5460-4417-a603-080e9b1fc309->task_1740422007565_ac64e2ef-6583-424f-ae49-38413e287f7b",
      "source": "task_1740422007565_7f5d2423-5460-4417-a603-080e9b1fc309",
      "target": "task_1740422007565_ac64e2ef-6583-424f-ae49-38413e287f7b",
      "parent": "runSequence_1740422007565_c9046c4b-f253-4b99-945f-70883e2ddcd4",
      "parallel": false
    },
    "group": "edges"
  },
  {
    "data": {
      "id": "task_1740422007565_ac64e2ef-6583-424f-ae49-38413e287f7b->task_1740422007565_b900f6d4-564b-4354-9872-001a31882cfa",
      "source": "task_1740422007565_ac64e2ef-6583-424f-ae49-38413e287f7b",
      "target": "task_1740422007565_b900f6d4-564b-4354-9872-001a31882cfa",
      "parent": "runSequence_1740422007565_c9046c4b-f253-4b99-945f-70883e2ddcd4",
      "parallel": false
    },
    "group": "edges"
  },
  {
    "data": {
      "id": "task_1740422007565_b900f6d4-564b-4354-9872-001a31882cfa->task_1740422007565_74169c2a-0426-4665-9045-a9eb0e0bc9a8",
      "source": "task_1740422007565_b900f6d4-564b-4354-9872-001a31882cfa",
      "target": "task_1740422007565_74169c2a-0426-4665-9045-a9eb0e0bc9a8",
      "parent": "runSequence_1740422007565_c9046c4b-f253-4b99-945f-70883e2ddcd4",
      "parallel": false
    },
    "group": "edges"
  },
  {
    "data": {
      "id": "runSequence_1740422007565_eaacf6b8-6420-4671-83f8-82acc73812a0->runInDepth_1740422007565_4669d06b-3d78-431e-97e7-99e2f54b6953",
      "source": "runSequence_1740422007565_eaacf6b8-6420-4671-83f8-82acc73812a0",
      "target": "runInDepth_1740422007565_4669d06b-3d78-431e-97e7-99e2f54b6953",
      "parent": "runInDepth_1740422007565_fc105f1b-e37f-4710-b7cb-f1f67e406609",
      "parallel": false
    },
    "group": "edges"
  },
  {
    "data": {
      "id": "runSequence_1740422007564_8fc8c562-e70f-44bd-a50d-9cc1caf413b4->runInDepth_1740422007565_fc105f1b-e37f-4710-b7cb-f1f67e406609",
      "source": "runSequence_1740422007564_8fc8c562-e70f-44bd-a50d-9cc1caf413b4",
      "target": "runInDepth_1740422007565_fc105f1b-e37f-4710-b7cb-f1f67e406609",
      "parent": "runInDepth_1740422007564_566a70b1-6b09-4a1e-9e75-8aed5c44476d",
      "parallel": false
    },
    "group": "edges"
  },
  {
    "data": {
      "id": "runSequence_1740422007564_0ee79e39-5f9f-41aa-80a4-537f449b47c7->runInDepth_1740422007564_566a70b1-6b09-4a1e-9e75-8aed5c44476d",
      "source": "runSequence_1740422007564_0ee79e39-5f9f-41aa-80a4-537f449b47c7",
      "target": "runInDepth_1740422007564_566a70b1-6b09-4a1e-9e75-8aed5c44476d",
      "parent": "runInDepth_1740422007564_3709665e-ba20-48e5-bdea-02ea83bce351",
      "parallel": false
    },
    "group": "edges"
  },
  {
    "data": {
      "id": "runSequence_1740422007564_3ec8dd2a-9d79-4e6f-b75d-f50ae17dc3b8->runInDepth_1740422007564_3709665e-ba20-48e5-bdea-02ea83bce351",
      "source": "runSequence_1740422007564_3ec8dd2a-9d79-4e6f-b75d-f50ae17dc3b8",
      "target": "runInDepth_1740422007564_3709665e-ba20-48e5-bdea-02ea83bce351",
      "parent": "runInDepth_1740422007564_e9574be5-6c13-4e74-814e-594179bf4ea8",
      "parallel": false
    },
    "group": "edges"
  },
  {
    "data": {
      "id": "runSequence_1740422007564_435a159e-a157-4979-9442-59895408bb95->runInDepth_1740422007564_e9574be5-6c13-4e74-814e-594179bf4ea8",
      "source": "runSequence_1740422007564_435a159e-a157-4979-9442-59895408bb95",
      "target": "runInDepth_1740422007564_e9574be5-6c13-4e74-814e-594179bf4ea8",
      "parent": "runInDepth_1740422007564_8242bbdd-eb4b-4119-a5e8-99c9d56da60a",
      "parallel": false
    },
    "group": "edges"
  },
  {
    "data": {
      "id": "runSequence_1740422007564_04a518e3-62e9-4649-9de2-c1630dca4f04->runInDepth_1740422007564_8242bbdd-eb4b-4119-a5e8-99c9d56da60a",
      "source": "runSequence_1740422007564_04a518e3-62e9-4649-9de2-c1630dca4f04",
      "target": "runInDepth_1740422007564_8242bbdd-eb4b-4119-a5e8-99c9d56da60a",
      "parent": "runInDepth_1740422007564_516dfdd7-ffef-47ef-b0e5-c0c2b4cf914e",
      "parallel": false
    },
    "group": "edges"
  },
  {
    "data": {
      "id": "runSequence_1740422007564_37f7b0cc-812c-42d2-90d1-f10c9b15f967->runInDepth_1740422007564_516dfdd7-ffef-47ef-b0e5-c0c2b4cf914e",
      "source": "runSequence_1740422007564_37f7b0cc-812c-42d2-90d1-f10c9b15f967",
      "target": "runInDepth_1740422007564_516dfdd7-ffef-47ef-b0e5-c0c2b4cf914e",
      "parent": "runInDepth_1740422007564_01cc5f8e-a4aa-4283-b9f3-341f1860d9f6",
      "parallel": false
    },
    "group": "edges"
  },
  {
    "data": {
      "id": "runSequence_1740422007563_b7242f4b-2356-4e8f-820b-70ee024b3880->runInDepth_1740422007564_01cc5f8e-a4aa-4283-b9f3-341f1860d9f6",
      "source": "runSequence_1740422007563_b7242f4b-2356-4e8f-820b-70ee024b3880",
      "target": "runInDepth_1740422007564_01cc5f8e-a4aa-4283-b9f3-341f1860d9f6",
      "parent": "runInDepth_1740422007563_3b5c0e86-f548-4ee7-9534-8a0e20137f9f",
      "parallel": false
    },
    "group": "edges"
  },
  {
    "data": {
      "id": "runSequence_1740422007563_c5c6bda0-011f-48fe-a6dd-4441b949247d->runInDepth_1740422007563_3b5c0e86-f548-4ee7-9534-8a0e20137f9f",
      "source": "runSequence_1740422007563_c5c6bda0-011f-48fe-a6dd-4441b949247d",
      "target": "runInDepth_1740422007563_3b5c0e86-f548-4ee7-9534-8a0e20137f9f",
      "parent": "runInDepth_1740422007563_a262665a-caec-47fc-9f20-cb2424baf6c1",
      "parallel": false
    },
    "group": "edges"
  },
  {
    "data": {
      "id": "runSequence_1740422007562_357a4cc1-104b-4744-ab37-bd283b198067->runInDepth_1740422007563_a262665a-caec-47fc-9f20-cb2424baf6c1",
      "source": "runSequence_1740422007562_357a4cc1-104b-4744-ab37-bd283b198067",
      "target": "runInDepth_1740422007563_a262665a-caec-47fc-9f20-cb2424baf6c1",
      "parent": "runInDepth_1740422007561_06a04954-ac06-410e-970d-49648e9462b1",
      "parallel": false
    },
    "group": "edges"
  }
]